crosscompute_views_barcode/__init__.py
crosscompute_views_barcode/constants.py
crosscompute_views_barcode/assets/barcode-output.js
crosscompute_views_barcode/assets/barcode.html
crosscompute_views_barcode/routines/__init__.py
crosscompute_views_barcode/routines/asset.py
crosscompute_views_barcode/routines/variable.py
crosscompute_views_barcode-0.2.2.dist-info/LICENSE.md
crosscompute_views_barcode-0.2.2.dist-info/METADATA
crosscompute_views_barcode-0.2.2.dist-info/WHEEL
crosscompute_views_barcode-0.2.2.dist-info/entry_points.txt
crosscompute_views_barcode-0.2.2.dist-info/top_level.txt
crosscompute_views_barcode-0.2.2.dist-info/zip-safe
crosscompute_views_barcode-0.2.2.dist-info/RECORD
