Metadata-Version: 2.1
Name: crosscompute-views-barcode
Version: 0.2.2
Summary: Scan barcodes in your automations.
Home-page: https://crosscompute.com
Author: CrossCompute Inc.
Author-email: support@crosscompute.com
License: MIT
Project-URL: Bug Tracker, https://github.com/crosscompute/crosscompute-views-barcode/issues
Project-URL: Documentation, https://github.com/crosscompute/crosscompute-views-barcode
Project-URL: Source Code, https://github.com/crosscompute/crosscompute-views-barcode
Platform: any
Classifier: Development Status :: 3 - Alpha
Classifier: Intended Audience :: Developers
Classifier: Intended Audience :: Information Technology
Classifier: Intended Audience :: Science/Research
Classifier: Intended Audience :: System Administrators
Classifier: License :: OSI Approved :: MIT License
Classifier: Operating System :: POSIX
Classifier: Programming Language :: Python :: 3
Requires-Python: >=3.10
License-File: LICENSE.md
Requires-Dist: crosscompute (>=0.9.4.6)
